{
  "id": "mek-s3-q22",
  "text": "Turbo Alternator is a generator operating on steam produced from waste heat of Main engine exhaust gases",
  "options": [
    {
      "id": "A",
      "text": "False"
    },
    {
      "id": "B",
      "text": "True"
    }
  ],
  "correctOptionId": "B",
  "courseId": "mek",
  "set": 3,
  "explanation": "A turbo-alternator, also known as an exhaust gas turbo-generator (EGTG), generates electricity by utilizing the waste heat energy from the main engine's exhaust gases to produce steam, which then drives a turbine coupled to an alternator."
}
