{
  "id": "pst-s2-q11",
  "text": "SART stands for:",
  "options": [
    {
      "id": "A",
      "text": "Search and Rescue Radar Transponder"
    },
    {
      "id": "B",
      "text": "Search and Rescue Radar Transformer"
    },
    {
      "id": "C",
      "text": "Search and Rescue Radar Transmission"
    },
    {
      "id": "D",
      "text": "Search and Rescue Radar Transmitor"
    }
  ],
  "correctOptionId": "A",
  "courseId": "pst",
  "set": 2,
  "explanation": "SART is the acronym for Search and Rescue Radar Transponder, which acts as a secondary aid to help rescue craft locate survivors via their onboard radar."
}
