{
  "id": "gsk-s12-q8",
  "text": "The split pin on a shackle prevents the pin from",
  "options": [
    {
      "id": "A",
      "text": "Getting corroded"
    },
    {
      "id": "B",
      "text": "Unlocking"
    },
    {
      "id": "C",
      "text": "Getting jammed"
    },
    {
      "id": "D",
      "text": "Getting stuck"
    }
  ],
  "correctOptionId": "B",
  "courseId": "gsk",
  "set": 12,
  "explanation": "A split pin (or cotter pin) inserted through a hole in the shackle pin and its head is used to secure the pin. It prevents the pin from backing out or unlocking due to vibration or movement, thus maintaining the shackle's connection."
}
