{
  "id": "mfa-s1-q10",
  "text": "Asthma attacks can be triggered by:",
  "options": [
    {
      "id": "A",
      "text": "A) Loud music"
    },
    {
      "id": "B",
      "text": "B) Too much fresh air activity"
    },
    {
      "id": "C",
      "text": "C) Not keeping to the diet"
    },
    {
      "id": "D",
      "text": "D) Nervous tension, allergy, or non-obvious cause"
    }
  ],
  "correctOptionId": "D",
  "courseId": "mfa",
  "set": 1,
  "explanation": "Asthma is a complex respiratory condition that can be triggered by a wide array of environmental, emotional, or physiological stressors. Nervous tension, allergens, and infections are common triggers identified in clinical maritime medical guides."
}
