{
  "id": "tasco-s3-q5",
  "text": "Pick the IEC symbol for explosion proof electrical protection?",
  "options": [
    {
      "id": "A",
      "text": "ex-e"
    },
    {
      "id": "B",
      "text": "ex-n"
    },
    {
      "id": "C",
      "text": "ex-d"
    },
    {
      "id": "D",
      "text": "ex-p"
    }
  ],
  "correctOptionId": "C",
  "courseId": "tasco",
  "set": 3,
  "explanation": "The symbol 'ex-d' denotes 'flameproof' (or explosion-proof) equipment, where the enclosure is designed to withstand an internal explosion without igniting the surrounding atmosphere."
}
