{
  "id": "fpff-s2-q39",
  "text": "Class K fire involves high fatty oils?",
  "options": [
    {
      "id": "A",
      "text": "A) True"
    },
    {
      "id": "B",
      "text": "B) False"
    }
  ],
  "correctOptionId": "A",
  "courseId": "fpff",
  "set": 2,
  "explanation": "Class K fires, also known as Class F in some regions, specifically involve combustible cooking oils and fats, such as high-fatty oils found in commercial kitchens. These require specialized extinguishing agents that create a saponification effect."
}
