{
  "id": "tasco-s2-q50",
  "text": "If there has been a fire in a closed unventilated compartment it may be unsafe to enter because of",
  "options": [
    {
      "id": "A",
      "text": "excess hydrogen"
    },
    {
      "id": "B",
      "text": "unburned carbon particles"
    },
    {
      "id": "C",
      "text": "excess nitrogen"
    },
    {
      "id": "D",
      "text": "a lack of oxygen"
    }
  ],
  "correctOptionId": "D",
  "courseId": "tasco",
  "set": 2,
  "explanation": "Fires consume oxygen rapidly, and the combustion products often include carbon monoxide and other toxic gases. An unventilated space post-fire is almost certainly oxygen-deficient."
}
