{
  "id": "tasco-s4-q35",
  "text": "What does \"V\" indicate in the pump illustration?",
  "options": [
    {
      "id": "A",
      "text": "Speed Torque Control Valve"
    },
    {
      "id": "B",
      "text": "Cofferdam Purging"
    },
    {
      "id": "C",
      "text": "Local Control Valve"
    },
    {
      "id": "D",
      "text": "Cofferdam Check Pipe **Correct answer : Cofferdam Purging**"
    }
  ],
  "correctOptionId": "B",
  "courseId": "tasco",
  "set": 4,
  "explanation": "In the context of Framo submerged pump monitoring, 'V' refers to the purging port or cofferdam purging connection. This is used to test for seal integrity by applying air/gas pressure and checking for leaks."
}
